pykeksikapi
