Metadata-Version: 2.1
Name: pykeksikapi
Version: 0.21
Summary: This library is needed for working with api.keksik.io. It provides convenient tools for processing the API of this website.
Home-page: https://github.com/unnecessaryss/pykeksikapi
Author: unneccessaryss
Requires-Python: >=3.9
License-File: LICENSE
